mcp_server_privatedns/__init__.py
mcp_server_privatedns/capi_client.py
mcp_server_privatedns/server.py
mcp_server_privatedns/tool_dnspod.py
mcp_server_privatedns/tool_privatedns.py
mcp_server_privatedns-0.1.1.dist-info/METADATA
mcp_server_privatedns-0.1.1.dist-info/WHEEL
mcp_server_privatedns-0.1.1.dist-info/entry_points.txt
mcp_server_privatedns-0.1.1.dist-info/RECORD
