Metadata-Version: 2.4
Name: mcp-server-privatedns
Version: 0.1.1
Summary: MCP Server for Tencent Cloud PrivateDNS
Requires-Python: >=3.10
Requires-Dist: mcp>=1.0.0
Requires-Dist: tencentcloud-sdk-python-common==3.0.1375
Requires-Dist: tencentcloud-sdk-python-dnspod==3.0.1375
Requires-Dist: tencentcloud-sdk-python-ecm>=3.0.1375
Requires-Dist: tencentcloud-sdk-python-privatedns>=3.0.1375
